nose2_timer/__init__.py
nose2_timer/plugin.py
nose2_timer-0.1.0.dist-info/LICENSE
nose2_timer-0.1.0.dist-info/LICENSE_nose-timer
nose2_timer-0.1.0.dist-info/METADATA
nose2_timer-0.1.0.dist-info/WHEEL
nose2_timer-0.1.0.dist-info/entry_points.txt
nose2_timer-0.1.0.dist-info/top_level.txt
nose2_timer-0.1.0.dist-info/RECORD
